src/__init__.py
src/__main__.py
src/cli.py
src/config.py
src/exceptions.py
src/log.py
src/mac.py
src/network.py
src/template/abp.json.tpl
src/template/config.json.tpl
src/template/device.json.tpl
src/template/device102.json.tpl
src/template/gateway.json.tpl
lora_mote_emulator-1.1.0.dist-info/LICENSE
lora_mote_emulator-1.1.0.dist-info/METADATA
lora_mote_emulator-1.1.0.dist-info/WHEEL
lora_mote_emulator-1.1.0.dist-info/entry_points.txt
lora_mote_emulator-1.1.0.dist-info/top_level.txt
lora_mote_emulator-1.1.0.dist-info/RECORD
